.gitignore
.gitmodules
CHANGES.rst
LICENSE.rst
MANIFEST.in
README.rst
setup.py
plone/__init__.py
plone.mockup.egg-info/PKG-INFO
plone.mockup.egg-info/SOURCES.txt
plone.mockup.egg-info/dependency_links.txt
plone.mockup.egg-info/entry_points.txt
plone.mockup.egg-info/namespace_packages.txt
plone.mockup.egg-info/not-zip-safe
plone.mockup.egg-info/top_level.txt