Metadata-Version: 1.1
Name: plone.mockup
Version: 1.0
Summary: Plone integration package for mockup
Home-page: https://github.com/plone/mockup
Author: Plone Foundation
Author-email: plone-developers@lists.sourceforge.net
License: BSD
Keywords: plone mockup
Platform: UNKNOWN
Classifier: Framework :: Plone
Classifier: Programming Language :: Python
Classifier: Topic :: Software Development :: Libraries :: Python Modules
